setup.py
distributions/Binomialdistribution.py
distributions/Gaussiandistribution.py
distributions/Generaldistribution.py
distributions/__init__.py
vardang_distributions.egg-info/PKG-INFO
vardang_distributions.egg-info/SOURCES.txt
vardang_distributions.egg-info/dependency_links.txt
vardang_distributions.egg-info/not-zip-safe
vardang_distributions.egg-info/top_level.txt